pybashutils/ChDir.py
pybashutils/__init__.py
pybashutils/getIP.py
pybashutils/getfreeport.py
pybashutils/logdemo.py
pybashutils/ulimit.py
pybashutils/ulimit_nofile.py
pybashutils/windows_linux_detect.py
pybashutils-0.6.2.dist-info/LICENSE.txt
pybashutils-0.6.2.dist-info/METADATA
pybashutils-0.6.2.dist-info/RECORD
pybashutils-0.6.2.dist-info/SOURCES.txt.new
pybashutils-0.6.2.dist-info/WHEEL
pybashutils-0.6.2.dist-info/dependency_links.txt.new
pybashutils-0.6.2.dist-info/entry_points.txt
pybashutils-0.6.2.dist-info/entry_points.txt.new
pybashutils-0.6.2.dist-info/requires.txt.new
pybashutils-0.6.2.dist-info/top_level.txt
pybashutils-0.6.2.dist-info/top_level.txt.new
