Metadata-Version: 2.1
Name: pybashutils
Version: 0.6.2
Summary: Cross-platform utilities for computer maintenance
Home-page: https://github.com/scivison/pybashutils
Author: Michael Hirsch, Ph.D.
License: UNKNOWN
Keywords: bash,networking,cmake
Platform: UNKNOWN
Classifier: Development Status :: 5 - Production/Stable
Classifier: Environment :: Console
Classifier: Intended Audience :: Information Technology
Classifier: Intended Audience :: System Administrators
Classifier: Operating System :: OS Independent
Classifier: Programming Language :: Python :: 3.6
Classifier: Programming Language :: Python :: 3.7
Classifier: Topic :: System :: Networking
Classifier: Topic :: Utilities
Requires-Python: >= 3.6
Provides-Extra: io
Provides-Extra: tests
Requires-Dist: colorama
Requires-Dist: binaryornot
Provides-Extra: io
Requires-Dist: pycurl; extra == 'io'
Provides-Extra: tests
Requires-Dist: pytest; extra == 'tests'
Requires-Dist: pytest-cov; extra == 'tests'
Requires-Dist: coveralls; extra == 'tests'
Requires-Dist: flake8; extra == 'tests'
Requires-Dist: mypy; extra == 'tests'
